usefulkarisch/__init__.py
usefulkarisch/classes.py
usefulkarisch/fastFunctions.py
usefulkarisch/functions.py
usefulkarisch/variables.py
usefulkarisch-0.0.11.dist-info/METADATA
usefulkarisch-0.0.11.dist-info/WHEEL
usefulkarisch-0.0.11.dist-info/licenses/LICENSE
usefulkarisch-0.0.11.dist-info/RECORD
