Metadata-Version: 2.4
Name: usefulkarisch
Version: 0.0.11
Summary: Useful functions for me
Author-email: Jack Karisch <jwkthrowaway@gmail.com>
License-Expression: MIT
License-File: LICENSE
Classifier: Operating System :: OS Independent
Classifier: Programming Language :: Python :: 3
Requires-Python: >=3.11
